{
  "label": "Grenade Launcher",
  "muzzle": { "x": 0, "y": 0.06, "z": -0.78 },
  "parts": [
    { "name": "stockPlate", "type": "box", "x": 0, "y": 0.0, "z": 0.4, "sx": 0.1, "sy": 0.22, "sz": 0.06, "color": 1316893 },
    { "name": "stockArmTop", "type": "box", "x": 0, "y": 0.07, "z": 0.3, "sx": 0.05, "sy": 0.045, "sz": 0.16, "color": 2765371 },
    { "name": "stockArmBottom", "type": "box", "x": 0, "y": -0.06, "z": 0.3, "sx": 0.05, "sy": 0.045, "sz": 0.16, "color": 2765371 },
    { "name": "receiver", "type": "box", "x": 0, "y": 0.04, "z": 0.12, "sx": 0.11, "sy": 0.14, "sz": 0.26, "color": 2304562 },
    { "name": "drum", "type": "cylinder", "x": 0, "y": 0.0, "z": -0.12, "sx": 0.155, "sy": 0.16, "sz": 0.155, "rotX": 1.571, "color": 3950420 },
    { "name": "drumFace", "type": "cylinder", "x": 0, "y": 0.0, "z": -0.205, "sx": 0.125, "sy": 0.015, "sz": 0.125, "rotX": 1.571, "color": 2304562 },
    { "name": "drumChamberTop", "type": "cylinder", "x": 0, "y": 0.08, "z": -0.21, "sx": 0.034, "sy": 0.02, "sz": 0.034, "rotX": 1.571, "color": 16747008 },
    { "name": "drumChamberL", "type": "cylinder", "x": -0.07, "y": -0.04, "z": -0.21, "sx": 0.034, "sy": 0.02, "sz": 0.034, "rotX": 1.571, "color": 16747008 },
    { "name": "drumChamberR", "type": "cylinder", "x": 0.07, "y": -0.04, "z": -0.21, "sx": 0.034, "sy": 0.02, "sz": 0.034, "rotX": 1.571, "color": 16747008 },
    { "name": "drumHub", "type": "cylinder", "x": 0, "y": 0.0, "z": -0.215, "sx": 0.03, "sy": 0.025, "sz": 0.03, "rotX": 1.571, "color": 16766474 },
    { "name": "barrel", "type": "cylinder", "x": 0, "y": 0.06, "z": -0.5, "sx": 0.052, "sy": 0.55, "sz": 0.052, "rotX": 1.571, "color": 1316893 },
    { "name": "barrelMouth", "type": "cylinder", "x": 0, "y": 0.06, "z": -0.76, "sx": 0.062, "sy": 0.05, "sz": 0.056, "rotX": 1.571, "color": 2765371 },
    { "name": "topRail", "type": "box", "x": 0, "y": 0.125, "z": 0.0, "sx": 0.06, "sy": 0.03, "sz": 0.5, "color": 1316893 },
    { "name": "ladderSight", "type": "box", "x": 0, "y": 0.18, "z": -0.18, "sx": 0.05, "sy": 0.08, "sz": 0.015, "rotX": -0.3, "color": 16766474 },
    { "name": "foregrip", "type": "box", "x": 0, "y": -0.08, "z": -0.45, "sx": 0.06, "sy": 0.14, "sz": 0.06, "rotX": 0.2, "color": 16747008 },
    { "name": "grip", "type": "box", "x": 0, "y": -0.12, "z": 0.18, "sx": 0.075, "sy": 0.17, "sz": 0.08, "rotX": -0.28, "color": 1316893 },
    { "name": "triggerGuard", "type": "box", "x": 0, "y": -0.07, "z": 0.08, "sx": 0.025, "sy": 0.012, "sz": 0.1, "color": 1316893 },
    { "name": "trigger", "type": "box", "x": 0, "y": -0.052, "z": 0.075, "sx": 0.014, "sy": 0.04, "sz": 0.014, "rotX": -0.15, "color": 9082789 }
  ]
}
