{
  "label": "Shotgun",
  "parts": [
    {
      "name": "frame",
      "type": "box",
      "x": 0,
      "y": -0.04,
      "z": -0.05,
      "sx": 0.127,
      "sy": 0.18,
      "sz": 0.454,
      "rotX": 0,
      "rotY": 0,
      "rotZ": 0,
      "color": 5943551
    },
    {
      "name": "slide",
      "type": "box",
      "x": 0,
      "y": 0.08,
      "z": -0.1,
      "sx": 0.13,
      "sy": 0.1,
      "sz": 0.528,
      "rotX": 0,
      "rotY": 0,
      "rotZ": 0,
      "color": 5943551
    },
    {
      "name": "barrel",
      "type": "cylinder",
      "x": 0,
      "y": 0.08,
      "z": -0.135,
      "sx": 0.048,
      "sy": 0.61,
      "sz": 0.042,
      "rotX": 1.571,
      "rotY": 0,
      "rotZ": 0,
      "color": 5943551
    },
    {
      "name": "grip",
      "type": "box",
      "x": 0,
      "y": -0.22,
      "z": 0.112,
      "sx": 0.106,
      "sy": 0.28,
      "sz": 0.13,
      "rotX": -0.25,
      "rotY": 0,
      "rotZ": 0,
      "color": 5943551
    },
    {
      "name": "triggerGuard",
      "type": "box",
      "x": 0,
      "y": -0.14,
      "z": -0.05,
      "sx": 0.042,
      "sy": 0.1,
      "sz": 0.13,
      "rotX": 0,
      "rotY": 0,
      "rotZ": 0,
      "color": 5943551
    },
    {
      "name": "mag",
      "type": "box",
      "x": 0,
      "y": -0.24,
      "z": 0.112,
      "sx": 0.095,
      "sy": 0.24,
      "sz": 0.119,
      "rotX": -0.25,
      "rotY": 0,
      "rotZ": 0,
      "color": 2320805
    },
    {
      "name": "topDetail",
      "type": "box",
      "x": 0,
      "y": 0.14,
      "z": -0.122,
      "sx": 0.086,
      "sy": 0.04,
      "sz": 0.352,
      "rotX": 0,
      "rotY": 0,
      "rotZ": 0,
      "color": 15989759
    },
    {
      "name": "sight",
      "type": "box",
      "x": 0,
      "y": 0.16,
      "z": -0.342,
      "sx": 0.022,
      "sy": 0.06,
      "sz": 0.022,
      "rotX": 0,
      "rotY": 0,
      "rotZ": 0,
      "color": 2320805
    },
    {
      "name": "glowL",
      "type": "box",
      "x": -0.07,
      "y": 0.02,
      "z": -0.1,
      "sx": 0.011,
      "sy": 0.04,
      "sz": 0.198,
      "rotX": 0,
      "rotY": 0,
      "rotZ": 0,
      "color": 16765286
    },
    {
      "name": "glowR",
      "type": "box",
      "x": 0.07,
      "y": 0.02,
      "z": -0.1,
      "sx": 0.011,
      "sy": 0.04,
      "sz": 0.198,
      "rotX": 0,
      "rotY": 0,
      "rotZ": 0,
      "color": 16765286
    }
  ],
  "muzzle": {
    "x": 0,
    "y": 0.08,
    "z": -0.92
  }
}